odoo8_addon_l10n_pe_crm_lead-8.0.1.0.0-py2.7-nspkg.pth
odoo_addons/l10n_pe_crm_lead/__openerp__.py
odoo_addons/l10n_pe_crm_lead/__init__.py
odoo_addons/l10n_pe_crm_lead/README.rst
odoo_addons/l10n_pe_crm_lead/view/crm_view.xml
odoo_addons/l10n_pe_crm_lead/i18n/es.po
odoo_addons/l10n_pe_crm_lead/i18n/es_PE.po
odoo_addons/l10n_pe_crm_lead/model/__init__.py
odoo_addons/l10n_pe_crm_lead/model/crm.py
odoo_addons/l10n_pe_crm_lead/wizard/__init__.py
odoo_addons/l10n_pe_crm_lead/wizard/crm_lead_to_opportunity.py
odoo8_addon_l10n_pe_crm_lead-8.0.1.0.0.dist-info/top_level.txt
odoo8_addon_l10n_pe_crm_lead-8.0.1.0.0.dist-info/WHEEL
odoo8_addon_l10n_pe_crm_lead-8.0.1.0.0.dist-info/RECORD
odoo8_addon_l10n_pe_crm_lead-8.0.1.0.0.dist-info/metadata.json
odoo8_addon_l10n_pe_crm_lead-8.0.1.0.0.dist-info/DESCRIPTION.rst
odoo8_addon_l10n_pe_crm_lead-8.0.1.0.0.dist-info/METADATA
odoo8_addon_l10n_pe_crm_lead-8.0.1.0.0.dist-info/namespace_packages.txt
